levyt/__init__.py
levyt/database.py
levyt/records.py
levyt-0.1.0.dist-info/LICENSE
levyt-0.1.0.dist-info/WHEEL
levyt-0.1.0.dist-info/METADATA
levyt-0.1.0.dist-info/RECORD
