Metadata-Version: 2.1
Name: levyt
Version: 0.1.0
Summary: Python db access made easy.
License: MIT
Author: Abram Isola
Author-email: abram@isola.mn
Requires-Python: >=3.7,<4.0
Classifier: License :: OSI Approved :: MIT License
Classifier: Programming Language :: Python :: 3
Classifier: Programming Language :: Python :: 3.7
Classifier: Programming Language :: Python :: 3.8
Classifier: Programming Language :: Python :: 3.9
Requires-Dist: SQLAlchemy (>=1.4.2,<2.0.0)
Requires-Dist: tablib (>=3.0.0,<4.0.0)
